bw2search/__init__.py
bw2search/indices.py
bw2search/schema.py
bw2search/search.py
bw2search-0.2.dist-info/DESCRIPTION.rst
bw2search-0.2.dist-info/METADATA
bw2search-0.2.dist-info/metadata.json
bw2search-0.2.dist-info/RECORD
bw2search-0.2.dist-info/top_level.txt
bw2search-0.2.dist-info/WHEEL
