Metadata-Version: 2.0
Name: bw2search
Version: 0.2
Summary: Search functionality for the Brightway2 LCA Framework
Home-page: https://bitbucket.org/cmutel/brightway2-search
Author: Chris Mutel
Author-email: cmutel@gmail.com
License: Copyright (c) 2014, Chris Mutel and ETH Zürich
Requires-Dist: bw2data
Requires-Dist: whoosh
